sqlalchemy_django_admin/__init__.py
sqlalchemy_django_admin/admin.py
sqlalchemy_django_admin/fields/__init__.py
sqlalchemy_django_admin/fields/composite.py
sqlalchemy_django_admin-0.0.6.dist-info/LICENSE
sqlalchemy_django_admin-0.0.6.dist-info/METADATA
sqlalchemy_django_admin-0.0.6.dist-info/WHEEL
sqlalchemy_django_admin-0.0.6.dist-info/top_level.txt
sqlalchemy_django_admin-0.0.6.dist-info/RECORD
